eventbus/__init__.py
eventbus/eventbus.py
eventbus/executor.py
eventbus/finder.py
eventbus/logger.py
eventbus/subscribe.py
eventbus/subscriber_method.py
eventbus/subscription.py
eventbus/utils.py
eventbus_py-0.0.3.dist-info/LICENSE
eventbus_py-0.0.3.dist-info/METADATA
eventbus_py-0.0.3.dist-info/WHEEL
eventbus_py-0.0.3.dist-info/top_level.txt
eventbus_py-0.0.3.dist-info/RECORD
