Metadata-Version: 2.1
Name: eventbus-py
Version: 0.0.3
Summary: An eventbus that used for FinanGen
Home-page: https://github.com/cyclegen/eventbus-py
Author: CycleGen
Author-email: pypi@cyclegen.cloud
License: UNKNOWN
Project-URL: Bug Tracker, https://github.com/cyclegen/eventbus-py/issues
Platform: UNKNOWN
Classifier: Programming Language :: Python :: 3
Classifier: License :: OSI Approved :: MIT License
Classifier: Operating System :: OS Independent
Classifier: Natural Language :: Chinese (Simplified)
Requires-Python: >=3.6
License-File: LICENSE
